package com.navprayas.bidding.utility;

import java.util.Calendar;
import java.util.concurrent.TimeUnit;

import kilim.Fiber;
import kilim.Mailbox;
import kilim.Pausable;
import kilim.State;
import kilim.Task;

import org.hibernate.SessionFactory;

import com.navprayas.bidding.common.form.BidItem;
import com.navprayas.bidding.engine.orm.Bid;

/*     */public class AuctioneerImpl
/*     */extends Task implements Auctioneer
/*     */{
	/* 20 */public static Mailbox<Bid> _mailbox = new Mailbox(200);
	/*     */public static Mailbox<Bid> _anouncebox;
	/*     */private static Auctioneer _instance;
	/* 23 */private boolean active = true;
	/*     */private SessionFactory sessionFactory;
	/* 25 */public static String SUCCESSREDISKEY = "bids::status::success";
	/* 26 */public static String FAILEDREDISKEY = "bids::status::failed";
	/* 27 */public static String AUTOBIDKEY = "bids::autobids";
	/* 28 */public static int NORMALBID = 1;
	/* 29 */public static int AUTOBID = 2;
	/* 30 */public static String NEXTBIDID = "bids::next_id";
	/*     */
	/*     */public static SQLPersister sqlPersister;
	/*     */
	/*     */public static final boolean $isWoven = true;

	/*     */
	/*     */public static synchronized Auctioneer getInstance()
	/*     */{
		/* 38 */if (_instance == null) {
			/* 39 */_instance = new AuctioneerImpl();
			/*     */}
		/* 41 */return _instance;
		/*     */}

	/*     */
	/*     */public Mailbox<Bid> getMailBox() {
		/* 45 */return _mailbox;
		/*     */}

	/*     */
	/*     */public void stopAuction() {
		/* 49 */this.active = false;
		/*     */}

	/*     */
	/*     */public void restart() {
		/* 53 */this.active = true;
		/*     */}

	/*     */
	/*     */public boolean startAuction()
	/*     */{
		/*     */try {
			/* 59 */Anouncer anouncer = Anouncer.getInstance();
			/* 60 */_anouncebox = anouncer.getMailBox();
			/* 61 */anouncer.start();
			/* 62 */sqlPersister = new SQLPersister(this.sessionFactory);
			/* 63 */sqlPersister.start();
			/* 64 */start();
			/* 65 */new GC().start();
			/*     */}
		/*     */catch (Exception e) {
			/* 68 */System.out.println("Database Engine not Ready!!!");
			/* 69 */return false;
			/*     */}
		/* 71 */return this.active;
		/*     */}

	/*     */
	/*     *//* Error */
	/*     */public void execute(Fiber arg1)
	/*     */throws Pausable, Exception
	/*     */{
		/*     */// Byte code:
		/*     */// 0: aload_1
		/*     */// 1: dup
		/*     */// 2: astore 9
		/*     */// 4: getfield 136 kilim/Fiber:pc I
		/*     */// 7: tableswitch default:+21->28, 0:+38->45, 1:+24->31
		/*     */// 28: invokestatic 139 kilim/Fiber:wrongPC ()V
		/*     */// 31: iconst_0
		/*     */// 32: istore 4
		/*     */// 34: aload 9
		/*     */// 36: invokevirtual 143 kilim/Fiber:getCallee ()Ljava/lang/Object;
		/*     */// 39: checkcast 36 kilim/Mailbox
		/*     */// 42: goto +12 -> 54
		/*     */// 45: iconst_0
		/*     */// 46: istore 4
		/*     */// 48: goto +1450 -> 1498
		/*     */// 51: getstatic 42
				// com/navprayas/bidding/engine/core/AuctioneerImpl:_mailbox
				// Lkilim/Mailbox;
		/*     */// 54: aload 9
		/*     */// 56: invokevirtual 147 kilim/Fiber:down ()Lkilim/Fiber;
		/*     */// 59: invokevirtual 151 kilim/Mailbox:get
				// (Lkilim/Fiber;)Ljava/lang/Object;
		/*     */// 62: aload 9
		/*     */// 64: invokevirtual 155 kilim/Fiber:up ()I
		/*     */// 67: tableswitch default:+61->128, 0:+61->128, 1:+61->128,
				// 2:+29->96, 3:+59->126
		/*     */// 96: pop
		/*     */// 97: new 157 kilim/State
		/*     */// 100: dup
		/*     */// 101: invokespecial 158 kilim/State:<init> ()V
		/*     */// 104: astore 10
		/*     */// 106: aload 10
		/*     */// 108: aload_0
		/*     */// 109: putfield 162 kilim/State:self Ljava/lang/Object;
		/*     */// 112: aload 10
		/*     */// 114: iconst_1
		/*     */// 115: putfield 163 kilim/State:pc I
		/*     */// 118: aload 9
		/*     */// 120: aload 10
		/*     */// 122: invokevirtual 167 kilim/Fiber:setState (Lkilim/State;)V
		/*     */// 125: return
		/*     */// 126: pop
		/*     */// 127: return
		/*     */// 128: checkcast 169 com/navprayas/bidding/engine/common/Bid
		/*     */// 131: astore_2
		/*     */// 132: getstatic 115 java/lang/System:out Ljava/io/PrintStream;
		/*     */// 135: new 171 java/lang/StringBuilder
		/*     */// 138: dup
		/*     */// 139: ldc -83
		/*     */// 141: invokespecial 175 java/lang/StringBuilder:<init>
				// (Ljava/lang/String;)V
		/*     */// 144: aload_2
		/*     */// 145: invokevirtual 179 java/lang/StringBuilder:append
				// (Ljava/lang/Object;)Ljava/lang/StringBuilder;
		/*     */// 148: invokevirtual 183 java/lang/StringBuilder:toString
				// ()Ljava/lang/String;
		/*     */// 151: invokevirtual 123 java/io/PrintStream:println
				// (Ljava/lang/String;)V
		/*     */// 154: aload_2
		/*     */// 155: invokevirtual 187
				// com/navprayas/bidding/engine/common/Bid:getBidItemId ()J
		/*     */// 158: invokestatic 193
				// com/navprayas/bidding/engine/redis/RedisCache:getBidItem
				// (J)Lcom/navprayas/bidding/engine/common/BidItem;
		/*     */// 161: astore_1
		/*     */// 162: aload_1
		/*     */// 163: invokevirtual 199
				// com/navprayas/bidding/engine/common/BidItem:getBid
				// ()Lcom/navprayas/bidding/engine/common/Bid;
		/*     */// 166: astore_3
		/*     */// 167: aload_1
		/*     */// 168: invokevirtual 202
				// com/navprayas/bidding/engine/common/BidItem:isAutoBidFlag ()Z
		/*     */// 171: istore 4
		/*     */// 173: getstatic 115 java/lang/System:out Ljava/io/PrintStream;
		/*     */// 176: new 171 java/lang/StringBuilder
		/*     */// 179: dup
		/*     */// 180: ldc -52
		/*     */// 182: invokespecial 175 java/lang/StringBuilder:<init>
				// (Ljava/lang/String;)V
		/*     */// 185: aload_3
		/*     */// 186: invokevirtual 179 java/lang/StringBuilder:append
				// (Ljava/lang/Object;)Ljava/lang/StringBuilder;
		/*     */// 189: invokevirtual 183 java/lang/StringBuilder:toString
				// ()Ljava/lang/String;
		/*     */// 192: invokevirtual 123 java/io/PrintStream:println
				// (Ljava/lang/String;)V
		/*     */// 195: getstatic 115 java/lang/System:out Ljava/io/PrintStream;
		/*     */// 198: new 171 java/lang/StringBuilder
		/*     */// 201: dup
		/*     */// 202: ldc -50
		/*     */// 204: invokespecial 175 java/lang/StringBuilder:<init>
				// (Ljava/lang/String;)V
		/*     */// 207: aload_0
		/*     */// 208: aload_1
		/*     */// 209: invokespecial 210
				// com/navprayas/bidding/engine/core/AuctioneerImpl:validateBid
				// (Lcom/navprayas/bidding/engine/common/BidItem;)Z
		/*     */// 212: invokevirtual 213 java/lang/StringBuilder:append
				// (Z)Ljava/lang/StringBuilder;
		/*     */// 215: invokevirtual 183 java/lang/StringBuilder:toString
				// ()Ljava/lang/String;
		/*     */// 218: invokevirtual 123 java/io/PrintStream:println
				// (Ljava/lang/String;)V
		/*     */// 221: aload_0
		/*     */// 222: aload_1
		/*     */// 223: invokespecial 210
				// com/navprayas/bidding/engine/core/AuctioneerImpl:validateBid
				// (Lcom/navprayas/bidding/engine/common/BidItem;)Z
		/*     */// 226: ifeq +1272 -> 1498
		/*     */// 229: aload_3
		/*     */// 230: ifnull +24 -> 254
		/*     */// 233: aload_3
		/*     */// 234: invokevirtual 217
				// com/navprayas/bidding/engine/common/Bid:getBidAmount ()D
		/*     */// 237: dconst_0
		/*     */// 238: dcmpl
		/*     */// 239: ifeq +15 -> 254
		/*     */// 242: aload_3
		/*     */// 243: invokevirtual 217
				// com/navprayas/bidding/engine/common/Bid:getBidAmount ()D
		/*     */// 246: aload_1
		/*     */// 247: invokevirtual 220
				// com/navprayas/bidding/engine/common/BidItem:getMinBidPrice
				// ()D
		/*     */// 250: dcmpg
		/*     */// 251: ifge +10 -> 261
		/*     */// 254: aload_1
		/*     */// 255: invokevirtual 220
				// com/navprayas/bidding/engine/common/BidItem:getMinBidPrice
				// ()D
		/*     */// 258: goto +7 -> 265
		/*     */// 261: aload_3
		/*     */// 262: invokevirtual 217
				// com/navprayas/bidding/engine/common/Bid:getBidAmount ()D
		/*     */// 265: dstore 5
		/*     */// 267: aload_2
		/*     */// 268: invokevirtual 223
				// com/navprayas/bidding/engine/common/Bid:getBidType ()I
		/*     */// 271: getstatic 56
				// com/navprayas/bidding/engine/core/AuctioneerImpl:NORMALBID I
		/*     */// 274: if_icmpne +377 -> 651
		/*     */// 277: getstatic 115 java/lang/System:out Ljava/io/PrintStream;
		/*     */// 280: ldc -31
		/*     */// 282: invokevirtual 123 java/io/PrintStream:println
				// (Ljava/lang/String;)V
		/*     */// 285: iload 4
		/*     */// 287: ifeq +314 -> 601
		/*     */// 290: aload_2
		/*     */// 291: invokevirtual 228
				// com/navprayas/bidding/engine/common/Bid:getBidderName
				// ()Ljava/lang/String;
		/*     */// 294: aload_3
		/*     */// 295: invokevirtual 228
				// com/navprayas/bidding/engine/common/Bid:getBidderName
				// ()Ljava/lang/String;
		/*     */// 298: invokevirtual 234 java/lang/String:equalsIgnoreCase
				// (Ljava/lang/String;)Z
		/*     */// 301: ifeq +90 -> 391
		/*     */// 304: aload_2
		/*     */// 305: invokevirtual 217
				// com/navprayas/bidding/engine/common/Bid:getBidAmount ()D
		/*     */// 308: aload_3
		/*     */// 309: invokevirtual 237
				// com/navprayas/bidding/engine/common/Bid:getAutoBidAmount ()D
		/*     */// 312: aload_1
		/*     */// 313: invokevirtual 240
				// com/navprayas/bidding/engine/common/BidItem:getMinBidIncrement
				// ()D
		/*     */// 316: dadd
		/*     */// 317: dcmpl
		/*     */// 318: iflt +63 -> 381
		/*     */// 321: aload_2
		/*     */// 322: ldc -14
		/*     */// 324: invokevirtual 245
				// com/navprayas/bidding/engine/common/Bid:setStatus
				// (Ljava/lang/String;)V
		/*     */// 327: aload_2
		/*     */// 328: new 247 java/util/Date
		/*     */// 331: dup
		/*     */// 332: invokespecial 248 java/util/Date:<init> ()V
		/*     */// 335: invokevirtual 252
				// com/navprayas/bidding/engine/common/Bid:setBidTime
				// (Ljava/util/Date;)V
		/*     */// 338: aload_1
		/*     */// 339: aload_2
		/*     */// 340: invokevirtual 256
				// com/navprayas/bidding/engine/common/BidItem:setBid
				// (Lcom/navprayas/bidding/engine/common/Bid;)V
		/*     */// 343: aload_3
		/*     */// 344: aload_3
		/*     */// 345: invokevirtual 237
				// com/navprayas/bidding/engine/common/Bid:getAutoBidAmount ()D
		/*     */// 348: invokevirtual 260
				// com/navprayas/bidding/engine/common/Bid:setBidAmount (D)V
		/*     */// 351: aload_3
		/*     */// 352: new 247 java/util/Date
		/*     */// 355: dup
		/*     */// 356: invokespecial 248 java/util/Date:<init> ()V
		/*     */// 359: invokevirtual 252
				// com/navprayas/bidding/engine/common/Bid:setBidTime
				// (Ljava/util/Date;)V
		/*     */// 362: aload_1
		/*     */// 363: new 247 java/util/Date
		/*     */// 366: dup
		/*     */// 367: invokespecial 248 java/util/Date:<init> ()V
		/*     */// 370: invokevirtual 263
				// com/navprayas/bidding/engine/common/BidItem:setLastUpdateTime
				// (Ljava/util/Date;)V
		/*     */// 373: aload_1
		/*     */// 374: iconst_1
		/*     */// 375: invokevirtual 267
				// com/navprayas/bidding/engine/common/BidItem:setAutoBidFlag
				// (Z)V
		/*     */// 378: goto +774 -> 1152
		/*     */// 381: aload_2
		/*     */// 382: ldc_w 269
		/*     */// 385: invokevirtual 245
				// com/navprayas/bidding/engine/common/Bid:setStatus
				// (Ljava/lang/String;)V
		/*     */// 388: goto +764 -> 1152
		/*     */// 391: aload_2
		/*     */// 392: invokevirtual 217
				// com/navprayas/bidding/engine/common/Bid:getBidAmount ()D
		/*     */// 395: aload_3
		/*     */// 396: invokevirtual 237
				// com/navprayas/bidding/engine/common/Bid:getAutoBidAmount ()D
		/*     */// 399: aload_1
		/*     */// 400: invokevirtual 240
				// com/navprayas/bidding/engine/common/BidItem:getMinBidIncrement
				// ()D
		/*     */// 403: dadd
		/*     */// 404: dcmpl
		/*     */// 405: iflt +87 -> 492
		/*     */// 408: aload_2
		/*     */// 409: ldc -14
		/*     */// 411: invokevirtual 245
				// com/navprayas/bidding/engine/common/Bid:setStatus
				// (Ljava/lang/String;)V
		/*     */// 414: aload_2
		/*     */// 415: new 247 java/util/Date
		/*     */// 418: dup
		/*     */// 419: invokespecial 248 java/util/Date:<init> ()V
		/*     */// 422: invokevirtual 252
				// com/navprayas/bidding/engine/common/Bid:setBidTime
				// (Ljava/util/Date;)V
		/*     */// 425: aload_1
		/*     */// 426: aload_2
		/*     */// 427: invokevirtual 256
				// com/navprayas/bidding/engine/common/BidItem:setBid
				// (Lcom/navprayas/bidding/engine/common/Bid;)V
		/*     */// 430: aload_3
		/*     */// 431: aload_3
		/*     */// 432: invokevirtual 237
				// com/navprayas/bidding/engine/common/Bid:getAutoBidAmount ()D
		/*     */// 435: invokevirtual 260
				// com/navprayas/bidding/engine/common/Bid:setBidAmount (D)V
		/*     */// 438: aload_3
		/*     */// 439: new 247 java/util/Date
		/*     */// 442: dup
		/*     */// 443: invokespecial 248 java/util/Date:<init> ()V
		/*     */// 446: invokevirtual 252
				// com/navprayas/bidding/engine/common/Bid:setBidTime
				// (Ljava/util/Date;)V
		/*     */// 449: aload_3
		/*     */// 450: ldc_w 269
		/*     */// 453: invokevirtual 245
				// com/navprayas/bidding/engine/common/Bid:setStatus
				// (Ljava/lang/String;)V
		/*     */// 456: aload_1
		/*     */// 457: iconst_0
		/*     */// 458: invokevirtual 267
				// com/navprayas/bidding/engine/common/BidItem:setAutoBidFlag
				// (Z)V
		/*     */// 461: aload_1
		/*     */// 462: ldc_w 271
		/*     */// 465: invokevirtual 274
				// com/navprayas/bidding/engine/common/BidItem:setAutoBidderName
				// (Ljava/lang/String;)V
		/*     */// 468: aload_1
		/*     */// 469: dconst_0
		/*     */// 470: invokevirtual 277
				// com/navprayas/bidding/engine/common/BidItem:setAutoBidAmount
				// (D)V
		/*     */// 473: aload_1
		/*     */// 474: lconst_0
		/*     */// 475: invokevirtual 281
				// com/navprayas/bidding/engine/common/BidItem:setAutoBidderId
				// (J)V
		/*     */// 478: aload_1
		/*     */// 479: new 247 java/util/Date
		/*     */// 482: dup
		/*     */// 483: invokespecial 248 java/util/Date:<init> ()V
		/*     */// 486: invokevirtual 263
				// com/navprayas/bidding/engine/common/BidItem:setLastUpdateTime
				// (Ljava/util/Date;)V
		/*     */// 489: goto +663 -> 1152
		/*     */// 492: aload_2
		/*     */// 493: invokevirtual 217
				// com/navprayas/bidding/engine/common/Bid:getBidAmount ()D
		/*     */// 496: aload_3
		/*     */// 497: invokevirtual 237
				// com/navprayas/bidding/engine/common/Bid:getAutoBidAmount ()D
		/*     */// 500: dcmpl
		/*     */// 501: ifne +49 -> 550
		/*     */// 504: aload_3
		/*     */// 505: aload_3
		/*     */// 506: invokevirtual 237
				// com/navprayas/bidding/engine/common/Bid:getAutoBidAmount ()D
		/*     */// 509: invokevirtual 260
				// com/navprayas/bidding/engine/common/Bid:setBidAmount (D)V
		/*     */// 512: aload_3
		/*     */// 513: new 247 java/util/Date
		/*     */// 516: dup
		/*     */// 517: invokespecial 248 java/util/Date:<init> ()V
		/*     */// 520: invokevirtual 252
				// com/navprayas/bidding/engine/common/Bid:setBidTime
				// (Ljava/util/Date;)V
		/*     */// 523: aload_3
		/*     */// 524: ldc -14
		/*     */// 526: invokevirtual 245
				// com/navprayas/bidding/engine/common/Bid:setStatus
				// (Ljava/lang/String;)V
		/*     */// 529: aload_2
		/*     */// 530: ldc_w 269
		/*     */// 533: invokevirtual 245
				// com/navprayas/bidding/engine/common/Bid:setStatus
				// (Ljava/lang/String;)V
		/*     */// 536: aload_1
		/*     */// 537: new 247 java/util/Date
		/*     */// 540: dup
		/*     */// 541: invokespecial 248 java/util/Date:<init> ()V
		/*     */// 544: invokevirtual 263
				// com/navprayas/bidding/engine/common/BidItem:setLastUpdateTime
				// (Ljava/util/Date;)V
		/*     */// 547: goto +605 -> 1152
		/*     */// 550: aload_3
		/*     */// 551: aload_2
		/*     */// 552: invokevirtual 217
				// com/navprayas/bidding/engine/common/Bid:getBidAmount ()D
		/*     */// 555: aload_1
		/*     */// 556: invokevirtual 240
				// com/navprayas/bidding/engine/common/BidItem:getMinBidIncrement
				// ()D
		/*     */// 559: dadd
		/*     */// 560: invokevirtual 260
				// com/navprayas/bidding/engine/common/Bid:setBidAmount (D)V
		/*     */// 563: aload_3
		/*     */// 564: new 247 java/util/Date
		/*     */// 567: dup
		/*     */// 568: invokespecial 248 java/util/Date:<init> ()V
		/*     */// 571: invokevirtual 252
				// com/navprayas/bidding/engine/common/Bid:setBidTime
				// (Ljava/util/Date;)V
		/*     */// 574: aload_3
		/*     */// 575: ldc -14
		/*     */// 577: invokevirtual 245
				// com/navprayas/bidding/engine/common/Bid:setStatus
				// (Ljava/lang/String;)V
		/*     */// 580: aload_2
		/*     */// 581: ldc_w 269
		/*     */// 584: invokevirtual 245
				// com/navprayas/bidding/engine/common/Bid:setStatus
				// (Ljava/lang/String;)V
		/*     */// 587: aload_1
		/*     */// 588: new 247 java/util/Date
		/*     */// 591: dup
		/*     */// 592: invokespecial 248 java/util/Date:<init> ()V
		/*     */// 595: invokevirtual 263
				// com/navprayas/bidding/engine/common/BidItem:setLastUpdateTime
				// (Ljava/util/Date;)V
		/*     */// 598: goto +554 -> 1152
		/*     */// 601: aload_2
		/*     */// 602: invokevirtual 217
				// com/navprayas/bidding/engine/common/Bid:getBidAmount ()D
		/*     */// 605: dload 5
		/*     */// 607: aload_1
		/*     */// 608: invokevirtual 240
				// com/navprayas/bidding/engine/common/BidItem:getMinBidIncrement
				// ()D
		/*     */// 611: dadd
		/*     */// 612: dcmpl
		/*     */// 613: iflt +28 -> 641
		/*     */// 616: aload_2
		/*     */// 617: ldc -14
		/*     */// 619: invokevirtual 245
				// com/navprayas/bidding/engine/common/Bid:setStatus
				// (Ljava/lang/String;)V
		/*     */// 622: aload_1
		/*     */// 623: aload_2
		/*     */// 624: invokevirtual 256
				// com/navprayas/bidding/engine/common/BidItem:setBid
				// (Lcom/navprayas/bidding/engine/common/Bid;)V
		/*     */// 627: aload_1
		/*     */// 628: new 247 java/util/Date
		/*     */// 631: dup
		/*     */// 632: invokespecial 248 java/util/Date:<init> ()V
		/*     */// 635: invokevirtual 263
				// com/navprayas/bidding/engine/common/BidItem:setLastUpdateTime
				// (Ljava/util/Date;)V
		/*     */// 638: goto +514 -> 1152
		/*     */// 641: aload_2
		/*     */// 642: ldc_w 269
		/*     */// 645: invokevirtual 245
				// com/navprayas/bidding/engine/common/Bid:setStatus
				// (Ljava/lang/String;)V
		/*     */// 648: goto +504 -> 1152
		/*     */// 651: aload_2
		/*     */// 652: invokevirtual 223
				// com/navprayas/bidding/engine/common/Bid:getBidType ()I
		/*     */// 655: getstatic 58
				// com/navprayas/bidding/engine/core/AuctioneerImpl:AUTOBID I
		/*     */// 658: if_icmpne +494 -> 1152
		/*     */// 661: getstatic 115 java/lang/System:out Ljava/io/PrintStream;
		/*     */// 664: ldc_w 283
		/*     */// 667: invokevirtual 123 java/io/PrintStream:println
				// (Ljava/lang/String;)V
		/*     */// 670: dload 5
		/*     */// 672: aload_1
		/*     */// 673: invokevirtual 240
				// com/navprayas/bidding/engine/common/BidItem:getMinBidIncrement
				// ()D
		/*     */// 676: dadd
		/*     */// 677: aload_2
		/*     */// 678: invokevirtual 237
				// com/navprayas/bidding/engine/common/Bid:getAutoBidAmount ()D
		/*     */// 681: dcmpl
		/*     */// 682: ifle +21 -> 703
		/*     */// 685: aload_2
		/*     */// 686: aload_2
		/*     */// 687: invokevirtual 237
				// com/navprayas/bidding/engine/common/Bid:getAutoBidAmount ()D
		/*     */// 690: invokevirtual 260
				// com/navprayas/bidding/engine/common/Bid:setBidAmount (D)V
		/*     */// 693: aload_2
		/*     */// 694: ldc_w 269
		/*     */// 697: invokevirtual 245
				// com/navprayas/bidding/engine/common/Bid:setStatus
				// (Ljava/lang/String;)V
		/*     */// 700: goto +452 -> 1152
		/*     */// 703: iload 4
		/*     */// 705: ifne +118 -> 823
		/*     */// 708: dconst_0
		/*     */// 709: dstore 7
		/*     */// 711: aload_3
		/*     */// 712: ifnull +24 -> 736
		/*     */// 715: aload_2
		/*     */// 716: invokevirtual 228
				// com/navprayas/bidding/engine/common/Bid:getBidderName
				// ()Ljava/lang/String;
		/*     */// 719: aload_3
		/*     */// 720: invokevirtual 228
				// com/navprayas/bidding/engine/common/Bid:getBidderName
				// ()Ljava/lang/String;
		/*     */// 723: invokevirtual 234 java/lang/String:equalsIgnoreCase
				// (Ljava/lang/String;)Z
		/*     */// 726: ifeq +10 -> 736
		/*     */// 729: dload 5
		/*     */// 731: dstore 7
		/*     */// 733: goto +12 -> 745
		/*     */// 736: dload 5
		/*     */// 738: aload_1
		/*     */// 739: invokevirtual 240
				// com/navprayas/bidding/engine/common/BidItem:getMinBidIncrement
				// ()D
		/*     */// 742: dadd
		/*     */// 743: dstore 7
		/*     */// 745: aload_2
		/*     */// 746: dload 7
		/*     */// 748: invokevirtual 260
				// com/navprayas/bidding/engine/common/Bid:setBidAmount (D)V
		/*     */// 751: getstatic 54
				// com/navprayas/bidding/engine/core/AuctioneerImpl:AUTOBIDKEY
				// Ljava/lang/String;
		/*     */// 754: aload_2
		/*     */// 755: invokestatic 287
				// com/navprayas/bidding/engine/redis/RedisCache:saveAutoBid
				// (Ljava/lang/String;Lcom/navprayas/bidding/engine/common/Bid;)V
		/*     */// 758: aload_2
		/*     */// 759: ldc -14
		/*     */// 761: invokevirtual 245
				// com/navprayas/bidding/engine/common/Bid:setStatus
				// (Ljava/lang/String;)V
		/*     */// 764: aload_2
		/*     */// 765: new 247 java/util/Date
		/*     */// 768: dup
		/*     */// 769: invokespecial 248 java/util/Date:<init> ()V
		/*     */// 772: invokevirtual 252
				// com/navprayas/bidding/engine/common/Bid:setBidTime
				// (Ljava/util/Date;)V
		/*     */// 775: aload_1
		/*     */// 776: iconst_1
		/*     */// 777: invokevirtual 267
				// com/navprayas/bidding/engine/common/BidItem:setAutoBidFlag
				// (Z)V
		/*     */// 780: aload_1
		/*     */// 781: aload_2
		/*     */// 782: invokevirtual 228
				// com/navprayas/bidding/engine/common/Bid:getBidderName
				// ()Ljava/lang/String;
		/*     */// 785: invokevirtual 274
				// com/navprayas/bidding/engine/common/BidItem:setAutoBidderName
				// (Ljava/lang/String;)V
		/*     */// 788: aload_1
		/*     */// 789: aload_2
		/*     */// 790: invokevirtual 237
				// com/navprayas/bidding/engine/common/Bid:getAutoBidAmount ()D
		/*     */// 793: invokevirtual 277
				// com/navprayas/bidding/engine/common/BidItem:setAutoBidAmount
				// (D)V
		/*     */// 796: aload_1
		/*     */// 797: aload_2
		/*     */// 798: invokevirtual 290
				// com/navprayas/bidding/engine/common/Bid:getBidderId ()J
		/*     */// 801: invokevirtual 281
				// com/navprayas/bidding/engine/common/BidItem:setAutoBidderId
				// (J)V
		/*     */// 804: aload_1
		/*     */// 805: aload_2
		/*     */// 806: invokevirtual 256
				// com/navprayas/bidding/engine/common/BidItem:setBid
				// (Lcom/navprayas/bidding/engine/common/Bid;)V
		/*     */// 809: aload_1
		/*     */// 810: new 247 java/util/Date
		/*     */// 813: dup
		/*     */// 814: invokespecial 248 java/util/Date:<init> ()V
		/*     */// 817: invokevirtual 263
				// com/navprayas/bidding/engine/common/BidItem:setLastUpdateTime
				// (Ljava/util/Date;)V
		/*     */// 820: goto +332 -> 1152
		/*     */// 823: aload_2
		/*     */// 824: invokevirtual 228
				// com/navprayas/bidding/engine/common/Bid:getBidderName
				// ()Ljava/lang/String;
		/*     */// 827: aload_3
		/*     */// 828: invokevirtual 228
				// com/navprayas/bidding/engine/common/Bid:getBidderName
				// ()Ljava/lang/String;
		/*     */// 831: invokevirtual 234 java/lang/String:equalsIgnoreCase
				// (Ljava/lang/String;)Z
		/*     */// 834: ifeq +81 -> 915
		/*     */// 837: aload_2
		/*     */// 838: dload 5
		/*     */// 840: invokevirtual 260
				// com/navprayas/bidding/engine/common/Bid:setBidAmount (D)V
		/*     */// 843: getstatic 54
				// com/navprayas/bidding/engine/core/AuctioneerImpl:AUTOBIDKEY
				// Ljava/lang/String;
		/*     */// 846: aload_2
		/*     */// 847: invokestatic 287
				// com/navprayas/bidding/engine/redis/RedisCache:saveAutoBid
				// (Ljava/lang/String;Lcom/navprayas/bidding/engine/common/Bid;)V
		/*     */// 850: aload_2
		/*     */// 851: ldc -14
		/*     */// 853: invokevirtual 245
				// com/navprayas/bidding/engine/common/Bid:setStatus
				// (Ljava/lang/String;)V
		/*     */// 856: aload_2
		/*     */// 857: new 247 java/util/Date
		/*     */// 860: dup
		/*     */// 861: invokespecial 248 java/util/Date:<init> ()V
		/*     */// 864: invokevirtual 252
				// com/navprayas/bidding/engine/common/Bid:setBidTime
				// (Ljava/util/Date;)V
		/*     */// 867: aload_1
		/*     */// 868: iconst_1
		/*     */// 869: invokevirtual 267
				// com/navprayas/bidding/engine/common/BidItem:setAutoBidFlag
				// (Z)V
		/*     */// 872: aload_1
		/*     */// 873: aload_2
		/*     */// 874: invokevirtual 228
				// com/navprayas/bidding/engine/common/Bid:getBidderName
				// ()Ljava/lang/String;
		/*     */// 877: invokevirtual 274
				// com/navprayas/bidding/engine/common/BidItem:setAutoBidderName
				// (Ljava/lang/String;)V
		/*     */// 880: aload_1
		/*     */// 881: aload_2
		/*     */// 882: invokevirtual 237
				// com/navprayas/bidding/engine/common/Bid:getAutoBidAmount ()D
		/*     */// 885: invokevirtual 277
				// com/navprayas/bidding/engine/common/BidItem:setAutoBidAmount
				// (D)V
		/*     */// 888: aload_1
		/*     */// 889: aload_2
		/*     */// 890: invokevirtual 290
				// com/navprayas/bidding/engine/common/Bid:getBidderId ()J
		/*     */// 893: invokevirtual 281
				// com/navprayas/bidding/engine/common/BidItem:setAutoBidderId
				// (J)V
		/*     */// 896: aload_1
		/*     */// 897: aload_2
		/*     */// 898: invokevirtual 256
				// com/navprayas/bidding/engine/common/BidItem:setBid
				// (Lcom/navprayas/bidding/engine/common/Bid;)V
		/*     */// 901: aload_1
		/*     */// 902: new 247 java/util/Date
		/*     */// 905: dup
		/*     */// 906: invokespecial 248 java/util/Date:<init> ()V
		/*     */// 909: invokevirtual 263
				// com/navprayas/bidding/engine/common/BidItem:setLastUpdateTime
				// (Ljava/util/Date;)V
		/*     */// 912: goto +240 -> 1152
		/*     */// 915: aload_2
		/*     */// 916: invokevirtual 237
				// com/navprayas/bidding/engine/common/Bid:getAutoBidAmount ()D
		/*     */// 919: aload_3
		/*     */// 920: invokevirtual 237
				// com/navprayas/bidding/engine/common/Bid:getAutoBidAmount ()D
		/*     */// 923: aload_1
		/*     */// 924: invokevirtual 240
				// com/navprayas/bidding/engine/common/BidItem:getMinBidIncrement
				// ()D
		/*     */// 927: dadd
		/*     */// 928: dcmpl
		/*     */// 929: iflt +102 -> 1031
		/*     */// 932: aload_2
		/*     */// 933: aload_3
		/*     */// 934: invokevirtual 237
				// com/navprayas/bidding/engine/common/Bid:getAutoBidAmount ()D
		/*     */// 937: aload_1
		/*     */// 938: invokevirtual 240
				// com/navprayas/bidding/engine/common/BidItem:getMinBidIncrement
				// ()D
		/*     */// 941: dadd
		/*     */// 942: invokevirtual 260
				// com/navprayas/bidding/engine/common/Bid:setBidAmount (D)V
		/*     */// 945: aload_2
		/*     */// 946: new 247 java/util/Date
		/*     */// 949: dup
		/*     */// 950: invokespecial 248 java/util/Date:<init> ()V
		/*     */// 953: invokevirtual 252
				// com/navprayas/bidding/engine/common/Bid:setBidTime
				// (Ljava/util/Date;)V
		/*     */// 956: aload_2
		/*     */// 957: ldc -14
		/*     */// 959: invokevirtual 245
				// com/navprayas/bidding/engine/common/Bid:setStatus
				// (Ljava/lang/String;)V
		/*     */// 962: aload_1
		/*     */// 963: aload_2
		/*     */// 964: invokevirtual 256
				// com/navprayas/bidding/engine/common/BidItem:setBid
				// (Lcom/navprayas/bidding/engine/common/Bid;)V
		/*     */// 967: aload_3
		/*     */// 968: aload_3
		/*     */// 969: invokevirtual 237
				// com/navprayas/bidding/engine/common/Bid:getAutoBidAmount ()D
		/*     */// 972: invokevirtual 260
				// com/navprayas/bidding/engine/common/Bid:setBidAmount (D)V
		/*     */// 975: aload_3
		/*     */// 976: new 247 java/util/Date
		/*     */// 979: dup
		/*     */// 980: invokespecial 248 java/util/Date:<init> ()V
		/*     */// 983: invokevirtual 252
				// com/navprayas/bidding/engine/common/Bid:setBidTime
				// (Ljava/util/Date;)V
		/*     */// 986: aload_3
		/*     */// 987: ldc_w 269
		/*     */// 990: invokevirtual 245
				// com/navprayas/bidding/engine/common/Bid:setStatus
				// (Ljava/lang/String;)V
		/*     */// 993: aload_1
		/*     */// 994: aload_2
		/*     */// 995: invokevirtual 228
				// com/navprayas/bidding/engine/common/Bid:getBidderName
				// ()Ljava/lang/String;
		/*     */// 998: invokevirtual 274
				// com/navprayas/bidding/engine/common/BidItem:setAutoBidderName
				// (Ljava/lang/String;)V
		/*     */// 1001: aload_1
		/*     */// 1002: aload_2
		/*     */// 1003: invokevirtual 237
				// com/navprayas/bidding/engine/common/Bid:getAutoBidAmount ()D
		/*     */// 1006: invokevirtual 277
				// com/navprayas/bidding/engine/common/BidItem:setAutoBidAmount
				// (D)V
		/*     */// 1009: aload_1
		/*     */// 1010: aload_2
		/*     */// 1011: invokevirtual 290
				// com/navprayas/bidding/engine/common/Bid:getBidderId ()J
		/*     */// 1014: invokevirtual 281
				// com/navprayas/bidding/engine/common/BidItem:setAutoBidderId
				// (J)V
		/*     */// 1017: aload_1
		/*     */// 1018: new 247 java/util/Date
		/*     */// 1021: dup
		/*     */// 1022: invokespecial 248 java/util/Date:<init> ()V
		/*     */// 1025: invokevirtual 263
				// com/navprayas/bidding/engine/common/BidItem:setLastUpdateTime
				// (Ljava/util/Date;)V
		/*     */// 1028: goto +117 -> 1145
		/*     */// 1031: aload_2
		/*     */// 1032: invokevirtual 237
				// com/navprayas/bidding/engine/common/Bid:getAutoBidAmount ()D
		/*     */// 1035: aload_3
		/*     */// 1036: invokevirtual 237
				// com/navprayas/bidding/engine/common/Bid:getAutoBidAmount ()D
		/*     */// 1039: dcmpl
		/*     */// 1040: ifne +49 -> 1089
		/*     */// 1043: aload_3
		/*     */// 1044: aload_3
		/*     */// 1045: invokevirtual 237
				// com/navprayas/bidding/engine/common/Bid:getAutoBidAmount ()D
		/*     */// 1048: invokevirtual 260
				// com/navprayas/bidding/engine/common/Bid:setBidAmount (D)V
		/*     */// 1051: aload_3
		/*     */// 1052: new 247 java/util/Date
		/*     */// 1055: dup
		/*     */// 1056: invokespecial 248 java/util/Date:<init> ()V
		/*     */// 1059: invokevirtual 252
				// com/navprayas/bidding/engine/common/Bid:setBidTime
				// (Ljava/util/Date;)V
		/*     */// 1062: aload_3
		/*     */// 1063: ldc -14
		/*     */// 1065: invokevirtual 245
				// com/navprayas/bidding/engine/common/Bid:setStatus
				// (Ljava/lang/String;)V
		/*     */// 1068: aload_2
		/*     */// 1069: ldc_w 269
		/*     */// 1072: invokevirtual 245
				// com/navprayas/bidding/engine/common/Bid:setStatus
				// (Ljava/lang/String;)V
		/*     */// 1075: aload_1
		/*     */// 1076: new 247 java/util/Date
		/*     */// 1079: dup
		/*     */// 1080: invokespecial 248 java/util/Date:<init> ()V
		/*     */// 1083: invokevirtual 263
				// com/navprayas/bidding/engine/common/BidItem:setLastUpdateTime
				// (Ljava/util/Date;)V
		/*     */// 1086: goto +59 -> 1145
		/*     */// 1089: aload_3
		/*     */// 1090: aload_2
		/*     */// 1091: invokevirtual 237
				// com/navprayas/bidding/engine/common/Bid:getAutoBidAmount ()D
		/*     */// 1094: aload_1
		/*     */// 1095: invokevirtual 240
				// com/navprayas/bidding/engine/common/BidItem:getMinBidIncrement
				// ()D
		/*     */// 1098: dadd
		/*     */// 1099: invokevirtual 260
				// com/navprayas/bidding/engine/common/Bid:setBidAmount (D)V
		/*     */// 1102: aload_3
		/*     */// 1103: new 247 java/util/Date
		/*     */// 1106: dup
		/*     */// 1107: invokespecial 248 java/util/Date:<init> ()V
		/*     */// 1110: invokevirtual 252
				// com/navprayas/bidding/engine/common/Bid:setBidTime
				// (Ljava/util/Date;)V
		/*     */// 1113: aload_3
		/*     */// 1114: ldc -14
		/*     */// 1116: invokevirtual 245
				// com/navprayas/bidding/engine/common/Bid:setStatus
				// (Ljava/lang/String;)V
		/*     */// 1119: aload_2
		/*     */// 1120: ldc_w 269
		/*     */// 1123: invokevirtual 245
				// com/navprayas/bidding/engine/common/Bid:setStatus
				// (Ljava/lang/String;)V
		/*     */// 1126: aload_2
		/*     */// 1127: aload_2
		/*     */// 1128: invokevirtual 237
				// com/navprayas/bidding/engine/common/Bid:getAutoBidAmount ()D
		/*     */// 1131: invokevirtual 260
				// com/navprayas/bidding/engine/common/Bid:setBidAmount (D)V
		/*     */// 1134: aload_1
		/*     */// 1135: new 247 java/util/Date
		/*     */// 1138: dup
		/*     */// 1139: invokespecial 248 java/util/Date:<init> ()V
		/*     */// 1142: invokevirtual 263
				// com/navprayas/bidding/engine/common/BidItem:setLastUpdateTime
				// (Ljava/util/Date;)V
		/*     */// 1145: getstatic 54
				// com/navprayas/bidding/engine/core/AuctioneerImpl:AUTOBIDKEY
				// Ljava/lang/String;
		/*     */// 1148: aload_2
		/*     */// 1149: invokestatic 287
				// com/navprayas/bidding/engine/redis/RedisCache:saveAutoBid
				// (Ljava/lang/String;Lcom/navprayas/bidding/engine/common/Bid;)V
		/*     */// 1152: iload 4
		/*     */// 1154: ifeq +198 -> 1352
		/*     */// 1157: aload_3
		/*     */// 1158: invokevirtual 293
				// com/navprayas/bidding/engine/common/Bid:getStatus
				// ()Ljava/lang/String;
		/*     */// 1161: astore 7
		/*     */// 1163: aload 7
		/*     */// 1165: ifnull +100 -> 1265
		/*     */// 1168: aload 7
		/*     */// 1170: ldc -14
		/*     */// 1172: invokevirtual 297 java/lang/String:equals
				// (Ljava/lang/Object;)Z
		/*     */// 1175: ifeq +90 -> 1265
		/*     */// 1178: getstatic 115 java/lang/System:out Ljava/io/PrintStream;
		/*     */// 1181: ldc_w 299
		/*     */// 1184: invokevirtual 123 java/io/PrintStream:println
				// (Ljava/lang/String;)V
		/*     */// 1187: getstatic 46
				// com/navprayas/bidding/engine/core/AuctioneerImpl:SUCCESSREDISKEY
				// Ljava/lang/String;
		/*     */// 1190: aload_3
		/*     */// 1191: invokestatic 302
				// com/navprayas/bidding/engine/redis/RedisCache:saveBid
				// (Ljava/lang/String;Lcom/navprayas/bidding/engine/common/Bid;)V
		/*     */// 1194: getstatic 50
				// com/navprayas/bidding/engine/core/AuctioneerImpl:FAILEDREDISKEY
				// Ljava/lang/String;
		/*     */// 1197: aload_2
		/*     */// 1198: invokestatic 302
				// com/navprayas/bidding/engine/redis/RedisCache:saveBid
				// (Ljava/lang/String;Lcom/navprayas/bidding/engine/common/Bid;)V
		/*     */// 1201: aload_3
		/*     */// 1202: invokevirtual 187
				// com/navprayas/bidding/engine/common/Bid:getBidItemId ()J
		/*     */// 1205: aload_3
		/*     */// 1206: invokevirtual 228
				// com/navprayas/bidding/engine/common/Bid:getBidderName
				// ()Ljava/lang/String;
		/*     */// 1209: aload_3
		/*     */// 1210: invokevirtual 223
				// com/navprayas/bidding/engine/common/Bid:getBidType ()I
		/*     */// 1213: iconst_1
		/*     */// 1214: if_icmpne +7 -> 1221
		/*     */// 1217: iconst_0
		/*     */// 1218: goto +4 -> 1222
		/*     */// 1221: iconst_1
		/*     */// 1222: aload_3
		/*     */// 1223: invokevirtual 217
				// com/navprayas/bidding/engine/common/Bid:getBidAmount ()D
		/*     */// 1226: invokestatic 306
				// com/navprayas/bidding/engine/redis/RedisCache:addBidder
				// (JLjava/lang/String;ZD)V
		/*     */// 1229: aload_2
		/*     */// 1230: invokevirtual 187
				// com/navprayas/bidding/engine/common/Bid:getBidItemId ()J
		/*     */// 1233: aload_2
		/*     */// 1234: invokevirtual 228
				// com/navprayas/bidding/engine/common/Bid:getBidderName
				// ()Ljava/lang/String;
		/*     */// 1237: iconst_0
		/*     */// 1238: aload_2
		/*     */// 1239: invokevirtual 217
				// com/navprayas/bidding/engine/common/Bid:getBidAmount ()D
		/*     */// 1242: invokestatic 306
				// com/navprayas/bidding/engine/redis/RedisCache:addBidder
				// (JLjava/lang/String;ZD)V
		/*     */// 1245: aload_3
		/*     */// 1246: invokestatic 309
				// com/navprayas/bidding/engine/redis/RedisCache:saveSuccessBid
				// (Lcom/navprayas/bidding/engine/common/Bid;)V
		/*     */// 1249: aload_0
		/*     */// 1250: aload_1
		/*     */// 1251: invokevirtual 313
				// com/navprayas/bidding/engine/core/AuctioneerImpl:setBidEndTime
				// (Lcom/navprayas/bidding/engine/common/BidItem;)V
		/*     */// 1254: getstatic 90
				// com/navprayas/bidding/engine/core/AuctioneerImpl:_anouncebox
				// Lkilim/Mailbox;
		/*     */// 1257: aload_3
		/*     */// 1258: invokevirtual 316 kilim/Mailbox:putnb
				// (Ljava/lang/Object;)Z
		/*     */// 1261: pop
		/*     */// 1262: goto +182 -> 1444
		/*     */// 1265: getstatic 115 java/lang/System:out Ljava/io/PrintStream;
		/*     */// 1268: ldc_w 318
		/*     */// 1271: invokevirtual 123 java/io/PrintStream:println
				// (Ljava/lang/String;)V
		/*     */// 1274: getstatic 46
				// com/navprayas/bidding/engine/core/AuctioneerImpl:SUCCESSREDISKEY
				// Ljava/lang/String;
		/*     */// 1277: aload_2
		/*     */// 1278: invokestatic 302
				// com/navprayas/bidding/engine/redis/RedisCache:saveBid
				// (Ljava/lang/String;Lcom/navprayas/bidding/engine/common/Bid;)V
		/*     */// 1281: getstatic 50
				// com/navprayas/bidding/engine/core/AuctioneerImpl:FAILEDREDISKEY
				// Ljava/lang/String;
		/*     */// 1284: aload_3
		/*     */// 1285: invokestatic 302
				// com/navprayas/bidding/engine/redis/RedisCache:saveBid
				// (Ljava/lang/String;Lcom/navprayas/bidding/engine/common/Bid;)V
		/*     */// 1288: aload_2
		/*     */// 1289: invokevirtual 187
				// com/navprayas/bidding/engine/common/Bid:getBidItemId ()J
		/*     */// 1292: aload_2
		/*     */// 1293: invokevirtual 228
				// com/navprayas/bidding/engine/common/Bid:getBidderName
				// ()Ljava/lang/String;
		/*     */// 1296: aload_2
		/*     */// 1297: invokevirtual 223
				// com/navprayas/bidding/engine/common/Bid:getBidType ()I
		/*     */// 1300: iconst_1
		/*     */// 1301: if_icmpne +7 -> 1308
		/*     */// 1304: iconst_0
		/*     */// 1305: goto +4 -> 1309
		/*     */// 1308: iconst_1
		/*     */// 1309: aload_2
		/*     */// 1310: invokevirtual 217
				// com/navprayas/bidding/engine/common/Bid:getBidAmount ()D
		/*     */// 1313: invokestatic 306
				// com/navprayas/bidding/engine/redis/RedisCache:addBidder
				// (JLjava/lang/String;ZD)V
		/*     */// 1316: aload_3
		/*     */// 1317: invokevirtual 187
				// com/navprayas/bidding/engine/common/Bid:getBidItemId ()J
		/*     */// 1320: aload_3
		/*     */// 1321: invokevirtual 228
				// com/navprayas/bidding/engine/common/Bid:getBidderName
				// ()Ljava/lang/String;
		/*     */// 1324: iconst_0
		/*     */// 1325: aload_3
		/*     */// 1326: invokevirtual 217
				// com/navprayas/bidding/engine/common/Bid:getBidAmount ()D
		/*     */// 1329: invokestatic 306
				// com/navprayas/bidding/engine/redis/RedisCache:addBidder
				// (JLjava/lang/String;ZD)V
		/*     */// 1332: aload_2
		/*     */// 1333: invokestatic 309
				// com/navprayas/bidding/engine/redis/RedisCache:saveSuccessBid
				// (Lcom/navprayas/bidding/engine/common/Bid;)V
		/*     */// 1336: aload_0
		/*     */// 1337: aload_1
		/*     */// 1338: invokevirtual 313
				// com/navprayas/bidding/engine/core/AuctioneerImpl:setBidEndTime
				// (Lcom/navprayas/bidding/engine/common/BidItem;)V
		/*     */// 1341: getstatic 90
				// com/navprayas/bidding/engine/core/AuctioneerImpl:_anouncebox
				// Lkilim/Mailbox;
		/*     */// 1344: aload_2
		/*     */// 1345: invokevirtual 316 kilim/Mailbox:putnb
				// (Ljava/lang/Object;)Z
		/*     */// 1348: pop
		/*     */// 1349: goto +95 -> 1444
		/*     */// 1352: aload_2
		/*     */// 1353: invokevirtual 293
				// com/navprayas/bidding/engine/common/Bid:getStatus
				// ()Ljava/lang/String;
		/*     */// 1356: ldc -14
		/*     */// 1358: invokevirtual 297 java/lang/String:equals
				// (Ljava/lang/Object;)Z
		/*     */// 1361: ifeq +67 -> 1428
		/*     */// 1364: getstatic 115 java/lang/System:out Ljava/io/PrintStream;
		/*     */// 1367: ldc_w 320
		/*     */// 1370: invokevirtual 123 java/io/PrintStream:println
				// (Ljava/lang/String;)V
		/*     */// 1373: getstatic 46
				// com/navprayas/bidding/engine/core/AuctioneerImpl:SUCCESSREDISKEY
				// Ljava/lang/String;
		/*     */// 1376: aload_2
		/*     */// 1377: invokestatic 302
				// com/navprayas/bidding/engine/redis/RedisCache:saveBid
				// (Ljava/lang/String;Lcom/navprayas/bidding/engine/common/Bid;)V
		/*     */// 1380: aload_2
		/*     */// 1381: invokestatic 309
				// com/navprayas/bidding/engine/redis/RedisCache:saveSuccessBid
				// (Lcom/navprayas/bidding/engine/common/Bid;)V
		/*     */// 1384: aload_0
		/*     */// 1385: aload_1
		/*     */// 1386: invokevirtual 313
				// com/navprayas/bidding/engine/core/AuctioneerImpl:setBidEndTime
				// (Lcom/navprayas/bidding/engine/common/BidItem;)V
		/*     */// 1389: aload_2
		/*     */// 1390: invokevirtual 187
				// com/navprayas/bidding/engine/common/Bid:getBidItemId ()J
		/*     */// 1393: aload_2
		/*     */// 1394: invokevirtual 228
				// com/navprayas/bidding/engine/common/Bid:getBidderName
				// ()Ljava/lang/String;
		/*     */// 1397: aload_2
		/*     */// 1398: invokevirtual 223
				// com/navprayas/bidding/engine/common/Bid:getBidType ()I
		/*     */// 1401: iconst_1
		/*     */// 1402: if_icmpne +7 -> 1409
		/*     */// 1405: iconst_0
		/*     */// 1406: goto +4 -> 1410
		/*     */// 1409: iconst_1
		/*     */// 1410: aload_2
		/*     */// 1411: invokevirtual 217
				// com/navprayas/bidding/engine/common/Bid:getBidAmount ()D
		/*     */// 1414: invokestatic 306
				// com/navprayas/bidding/engine/redis/RedisCache:addBidder
				// (JLjava/lang/String;ZD)V
		/*     */// 1417: getstatic 90
				// com/navprayas/bidding/engine/core/AuctioneerImpl:_anouncebox
				// Lkilim/Mailbox;
		/*     */// 1420: aload_2
		/*     */// 1421: invokevirtual 316 kilim/Mailbox:putnb
				// (Ljava/lang/Object;)Z
		/*     */// 1424: pop
		/*     */// 1425: goto +19 -> 1444
		/*     */// 1428: getstatic 115 java/lang/System:out Ljava/io/PrintStream;
		/*     */// 1431: ldc_w 322
		/*     */// 1434: invokevirtual 123 java/io/PrintStream:println
				// (Ljava/lang/String;)V
		/*     */// 1437: getstatic 50
				// com/navprayas/bidding/engine/core/AuctioneerImpl:FAILEDREDISKEY
				// Ljava/lang/String;
		/*     */// 1440: aload_2
		/*     */// 1441: invokestatic 302
				// com/navprayas/bidding/engine/redis/RedisCache:saveBid
				// (Ljava/lang/String;Lcom/navprayas/bidding/engine/common/Bid;)V
		/*     */// 1444: aload_1
		/*     */// 1445: invokestatic 325
				// com/navprayas/bidding/engine/redis/RedisCache:setBidItem
				// (Lcom/navprayas/bidding/engine/common/BidItem;)V
		/*     */// 1448: goto +50 -> 1498
		/*     */// 1451: aload 9
		/*     */// 1453: invokevirtual 328 kilim/Fiber:upEx ()I
		/*     */// 1456: tableswitch default:+24->1480, 0:+24->1480, 1:+24->1480
		/*     */// 1480: astore 5
		/*     */// 1482: aload_0
		/*     */// 1483: invokevirtual 330
				// com/navprayas/bidding/engine/core/AuctioneerImpl:stopAuction
				// ()V
		/*     */// 1486: getstatic 115 java/lang/System:out Ljava/io/PrintStream;
		/*     */// 1489: ldc_w 332
		/*     */// 1492: invokevirtual 123 java/io/PrintStream:println
				// (Ljava/lang/String;)V
		/*     */// 1495: aload 5
		/*     */// 1497: athrow
		/*     */// 1498: aload_0
		/*     */// 1499: getfield 66
				// com/navprayas/bidding/engine/core/AuctioneerImpl:active Z
		/*     */// 1502: ifne -1451 -> 51
		/*     */// 1505: return
		/*     */// Line number table:
		/*     */// Java source line #79 -> byte code offset #45
		/*     */// Java source line #81 -> byte code offset #48
		/*     */// Java source line #82 -> byte code offset #51
		/*     */// Java source line #83 -> byte code offset #132
		/*     */// Java source line #84 -> byte code offset #154
		/*     */// Java source line #85 -> byte code offset #162
		/*     */// Java source line #86 -> byte code offset #167
		/*     */// Java source line #87 -> byte code offset #173
		/*     */// Java source line #89 -> byte code offset #195
		/*     */// Java source line #91 -> byte code offset #221
		/*     */// Java source line #93 -> byte code offset #229
		/*     */// Java source line #97 -> byte code offset #267
		/*     */// Java source line #98 -> byte code offset #277
		/*     */// Java source line #102 -> byte code offset #285
		/*     */// Java source line #103 -> byte code offset #290
		/*     */// Java source line #104 -> byte code offset #304
		/*     */// Java source line #105 -> byte code offset #321
		/*     */// Java source line #106 -> byte code offset #327
		/*     */// Java source line #107 -> byte code offset #338
		/*     */// Java source line #108 -> byte code offset #343
		/*     */// Java source line #109 -> byte code offset #351
		/*     */// Java source line #110 -> byte code offset #362
		/*     */// Java source line #111 -> byte code offset #373
		/*     */// Java source line #114 -> byte code offset #381
		/*     */// Java source line #117 -> byte code offset #391
		/*     */// Java source line #118 -> byte code offset #408
		/*     */// Java source line #119 -> byte code offset #414
		/*     */// Java source line #120 -> byte code offset #425
		/*     */// Java source line #121 -> byte code offset #430
		/*     */// Java source line #122 -> byte code offset #438
		/*     */// Java source line #123 -> byte code offset #449
		/*     */// Java source line #124 -> byte code offset #456
		/*     */// Java source line #125 -> byte code offset #461
		/*     */// Java source line #126 -> byte code offset #468
		/*     */// Java source line #127 -> byte code offset #473
		/*     */// Java source line #128 -> byte code offset #478
		/*     */// Java source line #149 -> byte code offset #492
		/*     */// Java source line #150 -> byte code offset #504
		/*     */// Java source line #151 -> byte code offset #512
		/*     */// Java source line #152 -> byte code offset #523
		/*     */// Java source line #153 -> byte code offset #529
		/*     */// Java source line #154 -> byte code offset #536
		/*     */// Java source line #158 -> byte code offset #550
		/*     */// Java source line #159 -> byte code offset #563
		/*     */// Java source line #160 -> byte code offset #574
		/*     */// Java source line #161 -> byte code offset #580
		/*     */// Java source line #162 -> byte code offset #587
		/*     */// Java source line #169 -> byte code offset #601
		/*     */// Java source line #170 -> byte code offset #616
		/*     */// Java source line #171 -> byte code offset #622
		/*     */// Java source line #172 -> byte code offset #627
		/*     */// Java source line #175 -> byte code offset #641
		/*     */// Java source line #182 -> byte code offset #651
		/*     */// Java source line #183 -> byte code offset #661
		/*     */// Java source line #185 -> byte code offset #670
		/*     */// Java source line #186 -> byte code offset #685
		/*     */// Java source line #187 -> byte code offset #693
		/*     */// Java source line #190 -> byte code offset #703
		/*     */// Java source line #191 -> byte code offset #708
		/*     */// Java source line #192 -> byte code offset #711
		/*     */// Java source line #193 -> byte code offset #729
		/*     */// Java source line #196 -> byte code offset #736
		/*     */// Java source line #198 -> byte code offset #745
		/*     */// Java source line #199 -> byte code offset #751
		/*     */// Java source line #200 -> byte code offset #758
		/*     */// Java source line #201 -> byte code offset #764
		/*     */// Java source line #202 -> byte code offset #775
		/*     */// Java source line #203 -> byte code offset #780
		/*     */// Java source line #204 -> byte code offset #788
		/*     */// Java source line #205 -> byte code offset #796
		/*     */// Java source line #206 -> byte code offset #804
		/*     */// Java source line #207 -> byte code offset #809
		/*     */// Java source line #210 -> byte code offset #823
		/*     */// Java source line #211 -> byte code offset #837
		/*     */// Java source line #212 -> byte code offset #843
		/*     */// Java source line #213 -> byte code offset #850
		/*     */// Java source line #214 -> byte code offset #856
		/*     */// Java source line #215 -> byte code offset #867
		/*     */// Java source line #216 -> byte code offset #872
		/*     */// Java source line #217 -> byte code offset #880
		/*     */// Java source line #218 -> byte code offset #888
		/*     */// Java source line #219 -> byte code offset #896
		/*     */// Java source line #220 -> byte code offset #901
		/*     */// Java source line #223 -> byte code offset #915
		/*     */// Java source line #224 -> byte code offset #932
		/*     */// Java source line #225 -> byte code offset #945
		/*     */// Java source line #226 -> byte code offset #956
		/*     */// Java source line #227 -> byte code offset #962
		/*     */// Java source line #228 -> byte code offset #967
		/*     */// Java source line #229 -> byte code offset #975
		/*     */// Java source line #230 -> byte code offset #986
		/*     */// Java source line #231 -> byte code offset #993
		/*     */// Java source line #232 -> byte code offset #1001
		/*     */// Java source line #233 -> byte code offset #1009
		/*     */// Java source line #234 -> byte code offset #1017
		/*     */// Java source line #253 -> byte code offset #1031
		/*     */// Java source line #254 -> byte code offset #1043
		/*     */// Java source line #255 -> byte code offset #1051
		/*     */// Java source line #256 -> byte code offset #1062
		/*     */// Java source line #257 -> byte code offset #1068
		/*     */// Java source line #258 -> byte code offset #1075
		/*     */// Java source line #262 -> byte code offset #1089
		/*     */// Java source line #263 -> byte code offset #1102
		/*     */// Java source line #264 -> byte code offset #1113
		/*     */// Java source line #265 -> byte code offset #1119
		/*     */// Java source line #266 -> byte code offset #1126
		/*     */// Java source line #267 -> byte code offset #1134
		/*     */// Java source line #269 -> byte code offset #1145
		/*     */// Java source line #273 -> byte code offset #1152
		/*     */// Java source line #274 -> byte code offset #1157
		/*     */// Java source line #275 -> byte code offset #1163
		/*     */// Java source line #276 -> byte code offset #1178
		/*     */// Java source line #277 -> byte code offset #1187
		/*     */// Java source line #278 -> byte code offset #1194
		/*     */// Java source line #279 -> byte code offset #1201
		/*     */// Java source line #280 -> byte code offset #1205
		/*     */// Java source line #281 -> byte code offset #1209
		/*     */// Java source line #282 -> byte code offset #1222
		/*     */// Java source line #279 -> byte code offset #1226
		/*     */// Java source line #283 -> byte code offset #1229
		/*     */// Java source line #284 -> byte code offset #1233
		/*     */// Java source line #285 -> byte code offset #1237
		/*     */// Java source line #286 -> byte code offset #1238
		/*     */// Java source line #283 -> byte code offset #1242
		/*     */// Java source line #287 -> byte code offset #1245
		/*     */// Java source line #288 -> byte code offset #1249
		/*     */// Java source line #289 -> byte code offset #1254
		/*     */// Java source line #292 -> byte code offset #1265
		/*     */// Java source line #293 -> byte code offset #1274
		/*     */// Java source line #294 -> byte code offset #1281
		/*     */// Java source line #295 -> byte code offset #1288
		/*     */// Java source line #296 -> byte code offset #1292
		/*     */// Java source line #297 -> byte code offset #1296
		/*     */// Java source line #298 -> byte code offset #1309
		/*     */// Java source line #295 -> byte code offset #1313
		/*     */// Java source line #299 -> byte code offset #1316
		/*     */// Java source line #300 -> byte code offset #1320
		/*     */// Java source line #301 -> byte code offset #1324
		/*     */// Java source line #302 -> byte code offset #1325
		/*     */// Java source line #299 -> byte code offset #1329
		/*     */// Java source line #303 -> byte code offset #1332
		/*     */// Java source line #304 -> byte code offset #1336
		/*     */// Java source line #305 -> byte code offset #1341
		/*     */// Java source line #308 -> byte code offset #1352
		/*     */// Java source line #309 -> byte code offset #1364
		/*     */// Java source line #310 -> byte code offset #1373
		/*     */// Java source line #311 -> byte code offset #1380
		/*     */// Java source line #312 -> byte code offset #1384
		/*     */// Java source line #313 -> byte code offset #1389
		/*     */// Java source line #314 -> byte code offset #1393
		/*     */// Java source line #315 -> byte code offset #1397
		/*     */// Java source line #316 -> byte code offset #1410
		/*     */// Java source line #313 -> byte code offset #1414
		/*     */// Java source line #317 -> byte code offset #1417
		/*     */// Java source line #320 -> byte code offset #1428
		/*     */// Java source line #321 -> byte code offset #1437
		/*     */// Java source line #324 -> byte code offset #1444
		/*     */// Java source line #327 -> byte code offset #1451
		/*     */// Java source line #328 -> byte code offset #1482
		/*     */// Java source line #329 -> byte code offset #1486
		/*     */// Java source line #330 -> byte code offset #1495
		/*     */// Java source line #81 -> byte code offset #1498
		/*     */// Java source line #333 -> byte code offset #1505
		/*     */// Local variable table:
		/*     */// start length slot name signature
		/*     */// 45 1461 0 this AuctioneerImpl
		/*     */// 162 1336 1 bidItem BidItem
		/*     */// 132 1366 2 bid Bid
		/*     */// 167 1331 3 currentBid Bid
		/*     */// 48 1458 4 existsAutoBid boolean
		/*     */// 267 1181 5 currentPrice double
		/*     */// 1482 16 5 e Exception
		/*     */// 711 112 7 bidAmount double
		/*     */// 1163 189 7 status String
		/*     */// Exception table:
		/*     */// from to target type
		/*     */// 195 1448 1451 java/lang/Exception
		/*     */}

	/*     */
	/*     */public void execute()
	/*     */throws Pausable, Exception
	/*     */{
	}

	/*     */
	/*     */public void setBidEndTime(BidItem bidItem)
	/*     */{
		/* 336 */if (bidItem.getTimeExtAfterBid() != 0) {
			/* 337 */Calendar cal = Calendar.getInstance();
			/* 338 */cal.setTime(bidItem.getBidEndTime());
			/* 339 */cal.add(13, bidItem.getTimeExtAfterBid() * -1);
			/*     */
			/* 341 */if ((bidItem.getLastUpDateTime().after(cal.getTime()))
					|| (bidItem.getLastUpDateTime().equals(cal.getTime()))) {
				/* 342 */System.out.println("Before Bid End Time : "
						+ bidItem.getBidEndTime());
				/* 343 */cal.setTime(bidItem.getBidEndTime());
				/* 344 */cal.add(13, bidItem.getTimeExtAfterBid());
				/* 345 */bidItem.setBidEndTime(cal.getTime());
				/* 346 */System.out.println("After Bid End Time : "
						+ bidItem.getBidEndTime());
				/*     */}
			/*     */}
		/*     */}

	/*     */
	/*     */
	/*     */
	/*     */private boolean validateBid(BidItem bidItem)
	/*     */{
		/* 355 */if (bidItem == null)
			return false;
		/* 356 */if (!"ACTIVE".equals(bidItem.getStatusCode()))
			return false;
		/* 357 */if (bidItem.getBidEndTime().getTime() > System
				.currentTimeMillis())
			return true;
		/* 358 */if (System.currentTimeMillis()
				- bidItem.getBidEndTime().getTime() <= TimeUnit.SECONDS
					.toMillis(bidItem.getTimeExtAfterBid()))
			return true;
		/* 359 */if (System.currentTimeMillis()
				- bidItem.getLastUpDateTime().getTime() <= TimeUnit.SECONDS
					.toMillis(bidItem.getTimeExtAfterBid()))
			return true;
		/* 360 */return false;
		/*     */}

	/*     */
	/*     */class GC extends Task {
		public static final boolean $isWoven = true;

		/*     */
		/*     */GC() {
		}

		/*     */
		/* 367 */public void execute(Fiber paramFiber) throws Pausable {
			switch (paramFiber.pc) {
			default:
				//paramFiber.wrongPC();
			}

			/*     */
			/* 369 */
			/*     */{
//				/* 368 */RedisCache.cleanBidItem();
				/* 369 */Task.sleep(TimeUnit.SECONDS.toMillis(700L),
						paramFiber.down());
				switch (paramFiber.up()) {
				case 2:
					State localState = new State();
					localState.self = this;
					localState.pc = 1;
					paramFiber.setState(localState);
					return;
				}
				/*     */}
			/*     */}

		/*     */
		/*     */public void execute() throws Pausable
		/*     */{
		}
		/*     */
	}

	/*     */
	/*     */public void registerSessionFactory(SessionFactory factory) {
		/* 378 */this.sessionFactory = factory;
		/*     */}
	/*     */
}

/*
 * Location:
 * /home/cfeindia/Desktop/bidding-engine.jar!/com/navprayas/bidding/engine
 * /core/AuctioneerImpl.class Java compiler version: 6 (50.0) JD-Core Version:
 * 0.7.1
 */